iso3166_2/README.md
iso3166_2/__init__.py
iso3166_2/iso3166-2.json
iso3166_2/iso3166_2.py
iso3166_2-1.8.0.dist-info/LICENSE
iso3166_2-1.8.0.dist-info/METADATA
iso3166_2-1.8.0.dist-info/WHEEL
iso3166_2-1.8.0.dist-info/RECORD
