Metadata-Version: 2.3
Name: iso3166-2
Version: 1.8.0
Summary: A lightweight Python package, and accompanying RESTful API, used to access all of the world's most up-to-date and accurate ISO 3166-2 subdivision data, including: name, local/other name, code, parent code, type, latitude/longitude, flag and history.
License: MIT
Keywords: iso,iso3166,beautifulsoup,python,pypi,countries,country codes,iso3166-2,iso3166-1,alpha-2,iso3166-updates,iso3166-flag-icons,subdivisions,regions,dataset
Author: AJ McKenna
Author-email: amckenna41@qub.ac.uk
Maintainer: AJ McKenna
Maintainer-email: amckenna41@qub.ac.uk
Requires-Python: >=3.9,<4.0
Classifier: Development Status :: 5 - Production/Stable
Classifier: Environment :: Console
Classifier: Intended Audience :: Developers
Classifier: Intended Audience :: Information Technology
Classifier: Intended Audience :: Science/Research
Classifier: License :: Free For Educational Use
Classifier: License :: OSI Approved :: MIT License
Classifier: Natural Language :: English
Classifier: Programming Language :: Python :: 3
Classifier: Programming Language :: Python :: 3.9
Classifier: Programming Language :: Python :: 3.10
Classifier: Programming Language :: Python :: 3.11
Classifier: Programming Language :: Python :: 3.12
Classifier: Programming Language :: Python :: 3.13
Classifier: Programming Language :: Python :: 3 :: Only
Classifier: Programming Language :: Python :: Implementation :: PyPy
Classifier: Topic :: Scientific/Engineering
Classifier: Topic :: Scientific/Engineering :: Information Analysis
Classifier: Topic :: Software Development :: Libraries
Classifier: Topic :: Software Development :: Libraries :: Python Modules
Requires-Dist: Unidecode (>=1.3.8,<2.0.0)
Requires-Dist: iso3166 (>=2.1.1,<3.0.0)
Requires-Dist: natsort (>=8.4.0,<9.0.0)
Requires-Dist: thefuzz (>=0.22.1,<0.23.0)
Project-URL: Homepage, https://iso3166-2-api.vercel.app/api
Project-URL: documentation, https://iso3166-2.readthedocs.io/en/latest/
Project-URL: homepage, https://github.com/amckenna41/iso3166-2
Project-URL: repository, https://github.com/amckenna41/iso3166-2
